drepr-2.11.2.dist-info/METADATA
drepr-2.11.2.dist-info/WHEEL
drepr-2.11.2.dist-info/license_files/LICENSE
drepr/graph_deprecated.py
drepr/patches/xml_patch.py
drepr/patches/nc_patch.py
drepr/patches/__init__.py
drepr/patches/static_class_patch.py
drepr/patches/jp_propname_patch.py
drepr/__init__.py
drepr/utils/validator.py
drepr/utils/__init__.py
drepr/models/align.py
drepr/models/parse_v1/sm_parser.py
drepr/models/parse_v1/preprocessing_parser.py
drepr/models/parse_v1/__init__.py
drepr/models/parse_v1/path_parser.py
drepr/models/parse_v1/resource_parser.py
drepr/models/parse_v1/align_parser.py
drepr/models/parse_v1/attr_parser.py
drepr/models/resource.py
drepr/models/__init__.py
drepr/models/sm.py
drepr/models/preprocessing.py
drepr/models/drepr.py
drepr/models/drepr_builder.py
drepr/models/path.py
drepr/models/attr.py
drepr/models/parse_v2/sm_parser.py
drepr/models/parse_v2/__init__.py
drepr/models/parse_v2/path_parser.py
drepr/test.py
drepr/engine.py
drepr/executors/__init__.py
drepr/executors/cf_convention_map/cf_convention_map.py
drepr/executors/cf_convention_map/__init__.py
drepr/executors/preprocessing/__init__.py
drepr/executors/preprocessing/context.py
drepr/executors/preprocessing/pmap.py
drepr/executors/preprocessing/py_exec.py
drepr/executors/readers/shapefile.py
drepr/executors/readers/geotiff.py
drepr/executors/readers/np_dict.py
drepr/executors/readers/__init__.py
drepr/executors/readers/netcdf.py
drepr/executors/readers/reader_container.py
drepr/executors/readers/ra_reader.py
drepr/outputs/data_model.md
drepr/outputs/__init__.py
drepr/outputs/prop_data_ndarray.py
drepr/outputs/readme.md
drepr/outputs/base_lst_output_class.py
drepr/outputs/graph_backend/__init__.py
drepr/outputs/graph_backend/graph_class.py
drepr/outputs/graph_backend/graph_backend.py
drepr/outputs/graph_backend/graph_record.py
drepr/outputs/graph_backend/subset_graph_class.py
drepr/outputs/graph_backend/graph_predicate.py
drepr/outputs/graph_backend/lst_graph_class.py
drepr/outputs/base_output_predicate.py
drepr/outputs/base_record.py
drepr/outputs/array_backend/array_class.py
drepr-2.11.2.dist-info/RECORD
