Metadata-Version: 2.1
Name: drepr
Version: 2.11.2
Requires-Dist: orjson >=3.6.8, <4.0.0
Requires-Dist: ruamel.yaml >=0.17.21
Requires-Dist: xmltodict >=0.13.0
Requires-Dist: numpy >=1.22.4
Requires-Dist: pillow >=9.1.1
Requires-Dist: fiona >=1.0.0 ; extra == 'fiona'
Requires-Dist: netCDF4 >=1.0.0 ; extra == 'netcdf'
Provides-Extra: fiona
Provides-Extra: netcdf
License-File: LICENSE
Summary: Data Representation Language for Reading Heterogeneous Datasets
Author: Binh Vu <binh@toan2.com>
Author-email: Binh Vu <binh@toan2.com>
Requires-Python: >=3.8
Project-URL: homepage, https://github.com/usc-isi-i2/d-repr
Project-URL: repository, https://github.com/usc-isi-i2/d-repr
